MANIFEST.in
setup.py
idmyteam/__init__.py
idmyteam/apps.py
idmyteam/helpers.py
idmyteam/structs.py
idmyteam.egg-info/PKG-INFO
idmyteam.egg-info/SOURCES.txt
idmyteam.egg-info/dependency_links.txt
idmyteam.egg-info/top_level.txt
idmyteam/static/css/main.css
idmyteam/static/css/main.css.map
idmyteam/static/css/main.sass
idmyteam/static/css/idmyteam-sass/_variables.sass
idmyteam/static/css/idmyteam-sass/main.sass
idmyteam/static/css/idmyteam-sass/modules/_all.sass
idmyteam/static/css/idmyteam-sass/modules/_btn.sass
idmyteam/static/css/idmyteam-sass/modules/_card.sass
idmyteam/static/css/idmyteam-sass/modules/_flash.sass
idmyteam/static/css/idmyteam-sass/modules/_form.sass
idmyteam/static/css/idmyteam-sass/modules/_material.sass
idmyteam/static/css/idmyteam-sass/modules/_nav.sass
idmyteam/static/css/idmyteam-sass/partials/_base.sass
idmyteam/static/css/idmyteam-sass/partials/_helpers.sass
idmyteam/static/css/idmyteam-sass/vendors/animate.css
idmyteam/static/css/idmyteam-sass/vendors/materialize-sass/materialize.scss
idmyteam/static/css/idmyteam-sass/vendors/materialize-sass/components/_badges.scss
idmyteam/static/css/idmyteam-sass/vendors/materialize-sass/components/_buttons.scss
idmyteam/static/css/idmyteam-sass/vendors/materialize-sass/components/_cards.scss
idmyteam/static/css/idmyteam-sass/vendors/materialize-sass/components/_carousel.scss
idmyteam/static/css/idmyteam-sass/vendors/materialize-sass/components/_chips.scss
idmyteam/static/css/idmyteam-sass/vendors/materialize-sass/components/_collapsible.scss
idmyteam/static/css/idmyteam-sass/vendors/materialize-sass/components/_color.scss
idmyteam/static/css/idmyteam-sass/vendors/materialize-sass/components/_dropdown.scss
idmyteam/static/css/idmyteam-sass/vendors/materialize-sass/components/_global.scss
idmyteam/static/css/idmyteam-sass/vendors/materialize-sass/components/_grid.scss
idmyteam/static/css/idmyteam-sass/vendors/materialize-sass/components/_icons-material-design.scss
idmyteam/static/css/idmyteam-sass/vendors/materialize-sass/components/_materialbox.scss
