Metadata-Version: 1.0
Name: idmyteam
Version: 1.7.0
Summary: Base django files for idmyteam-client and idmyteam-server
Home-page: https://idmy.team/
Author: Maximilian Mitchell
Author-email: max@max.me.uk
License: BSD-3-Clause
Platform: UNKNOWN
